mogonet/__init__.py
mogonet/feat_importance.py
mogonet/models.py
mogonet/prepare_trte_data.py
mogonet/test_mogonet.py
mogonet/train_mogonet.py
mogonet/train_test.py
mogonet/utils.py
mogonet-2.0.1.dist-info/METADATA
mogonet-2.0.1.dist-info/WHEEL
mogonet-2.0.1.dist-info/top_level.txt
mogonet-2.0.1.dist-info/RECORD
